Workbook

Sheet الملخص
A1: ملخص الوظائف حسب الموديول والتطبيق
A2: الأعداد محسوبة بمعادلات من ورقة «قائمة الوظائف». «ضمن النطاق» = المخطط التفصيلي + قائمة وظائف المورّد (محسوبة افتراضياً)؛ «من واقع الخبرة» = مقترحة وغير محسوبة حتى يقرر الفريق تضمينها.
A4: الموديول (الإدارة) | B4: التطبيق | C4: Application | D4: تابع لـ / ملاحظات | E4: إجمالي الوظائف | F4: المخطط التفصيلي | G4: قائمة المورّد | H4: من واقع الخبرة | I4: محسوبة افتراضياً | J4: يعمل تشغيلياً (حسب المورّد)
A5: إدارة الموارد البشرية والخدمات | B5: شؤون العاملين | C5: Personnel Affairs | E5: =COUNTIFS('قائمة الوظائف'!$D$5:$D$517,$B5) -> 40 | F5: =COUNTIFS('قائمة الوظائف'!$D$5:$D$517,$B5,'قائمة الوظائف'!$J$5:$J$517,"المخطط التفصيلي") -> 20 | G5: =COUNTIFS('قائمة الوظائف'!$D$5:$D$517,$B5,'قائمة الوظائف'!$J$5:$J$517,"قائمة وظائف المورّد") -> 13 | H5: =COUNTIFS('قائمة الوظائف'!$D$5:$D$517,$B5,'قائمة الوظائف'!$J$5:$J$517,"من واقع الخبرة") -> 7 | I5: =COUNTIFS('قائمة الوظائف'!$D$5:$D$517,$B5,'قائمة الوظائف'!$M$5:$M$517,"نعم") -> 33 | J5: =COUNTIFS('قائمة الوظائف'!$D$5:$D$517,$B5,'قائمة الوظائف'!$L$5:$L$517,"يعمل تشغيلياً") -> 10
A6: إدارة الموارد البشرية والخدمات | B6: التوظيف | C6: Recruitment | D6: ضمن شؤون العاملين | E6: =COUNTIFS('قائمة الوظائف'!$D$5:$D$517,$B6) -> 15 | F6: =COUNTIFS('قائمة الوظائف'!$D$5:$D$517,$B6,'قائمة الوظائف'!$J$5:$J$517,"المخطط التفصيلي") -> 13 | G6: =COUNTIFS('قائمة الوظائف'!$D$5:$D$517,$B6,'قائمة الوظائف'!$J$5:$J$517,"قائمة وظائف المورّد") -> 1 | H6: =COUNTIFS('قائمة الوظائف'!$D$5:$D$517,$B6,'قائمة الوظائف'!$J$5:$J$517,"من واقع الخبرة") -> 1 | I6: =COUNTIFS('قائمة الوظائف'!$D$5:$D$517,$B6,'قائمة الوظائف'!$M$5:$M$517,"نعم") -> 14 | J6: =COUNTIFS('قائمة الوظائف'!$D$5:$D$517,$B6,'قائمة الوظائف'!$L$5:$L$517,"يعمل تشغيلياً") -> 1
A7: إدارة الموارد البشرية والخدمات | B7: الحضور والانصراف | C7: Time & Attendance | E7: =COUNTIFS('قائمة الوظائف'!$D$5:$D$517,$B7) -> 33 | F7: =COUNTIFS('قائمة الوظائف'!$D$5:$D$517,$B7,'قائمة الوظائف'!$J$5:$J$517,"المخطط التفصيلي") -> 13 | G7: =COUNTIFS('قائمة الوظائف'!$D$5:$D$517,$B7,'قائمة الوظائف'!$J$5:$J$517,"قائمة وظائف المورّد") -> 18 | H7: =COUNTIFS('قائمة الوظائف'!$D$5:$D$517,$B7,'قائمة الوظائف'!$J$5:$J$517,"من واقع الخبرة") -> 2 | I7: =COUNTIFS('قائمة الوظائف'!$D$5:$D$517,$B7,'قائمة الوظائف'!$M$5:$M$517,"نعم") -> 31 | J7: =COUNTIFS('قائمة الوظائف'!$D$5:$D$517,$B7,'قائمة الوظائف'!$L$5:$L$517,"يعمل تشغيلياً") -> 17
A8: إدارة الموارد البشرية والخدمات | B8: الإجازات | C8: Leave | E8: =COUNTIFS('قائمة الوظائف'!$D$5:$D$517,$B8) -> 15 | F8: =COUNTIFS('قائمة الوظائف'!$D$5:$D$517,$B8,'قائمة الوظائف'!$J$5:$J$517,"المخطط التفصيلي") -> 5 | G8: =COUNTIFS('قائمة الوظائف'!$D$5:$D$517,$B8,'قائمة الوظائف'!$J$5:$J$517,"قائمة وظائف المورّد") -> 7 | H8: =COUNTIFS('قائمة الوظائف'!$D$5:$D$517,$B8,'قائمة الوظائف'!$J$5:$J$517,"من واقع الخبرة") -> 3 | I8: =COUNTIFS('قائمة الوظائف'!$D$5:$D$517,$B8,'قائمة الوظائف'!$M$5:$M$517,"نعم") -> 12 | J8: =COUNTIFS('قائمة الوظائف'!$D$5:$D$517,$B8,'قائمة الوظائف'!$L$5:$L$517,"يعمل تشغيلياً") -> 7
A9: إدارة الموارد البشرية والخدمات | B9: المرتبات والسلف | C9: Payroll & Advances | E9: =COUNTIFS('قائمة الوظائف'!$D$5:$D$517,$B9) -> 32 | F9: =COUNTIFS('قائمة الوظائف'!$D$5:$D$517,$B9,'قائمة الوظائف'!$J$5:$J$517,"المخطط التفصيلي") -> 14 | G9: =COUNTIFS('قائمة الوظائف'!$D$5:$D$517,$B9,'قائمة الوظائف'!$J$5:$J$517,"قائمة وظائف المورّد") -> 11 | H9: =COUNTIFS('قائمة الوظائف'!$D$5:$D$517,$B9,'قائمة الوظائف'!$J$5:$J$517,"من واقع الخبرة") -> 7 | I9: =COUNTIFS('قائمة الوظائف'!$D$5:$D$517,$B9,'قائمة الوظائف'!$M$5:$M$517,"نعم") -> 25 | J9: =COUNTIFS('قائمة الوظائف'!$D$5:$D$517,$B9,'قائمة الوظائف'!$L$5:$L$517,"يعمل تشغيلياً") -> 8
A10: إدارة الموارد البشرية والخدمات | B10: التقييم | C10: Appraisal | D10: ضمن المرتبات | E10: =COUNTIFS('قائمة الوظائف'!$D$5:$D$517,$B10) -> 14 | F10: =COUNTIFS('قائمة الوظائف'!$D$5:$D$517,$B10,'قائمة الوظائف'!$J$5:$J$517,"المخطط التفصيلي") -> 8 | G10: =COUNTIFS('قائمة الوظائف'!$D$5:$D$517,$B10,'قائمة الوظائف'!$J$5:$J$517,"قائمة وظائف المورّد") -> 2 | H10: =COUNTIFS('قائمة الوظائف'!$D$5:$D$517,$B10,'قائمة الوظائف'!$J$5:$J$517,"من واقع الخبرة") -> 4 | I10: =COUNTIFS('قائمة الوظائف'!$D$5:$D$517,$B10,'قائمة الوظائف'!$M$5:$M$517,"نعم") -> 10 | J10: =COUNTIFS('قائمة الوظائف'!$D$5:$D$517,$B10,'قائمة الوظائف'!$L$5:$L$517,"يعمل تشغيلياً") -> 1
A11: إدارة الموارد البشرية والخدمات | B11: الطلبات ومسارات الاعتماد | C11: Requests & Approval Workflows | D11: وحدة غير واردة في المخطط | E11: =COUNTIFS('قائمة الوظائف'!$D$5:$D$517,$B11) -> 11 | F11: =COUNTIFS('قائمة الوظائف'!$D$5:$D$517,$B11,'قائمة الوظائف'!$J$5:$J$517,"المخطط التفصيلي") -> 0 | G11: =COUNTIFS('قائمة الوظائف'!$D$5:$D$517,$B11,'قائمة الوظائف'!$J$5:$J$517,"قائمة وظائف المورّد") -> 11 | H11: =COUNTIFS('قائمة الوظائف'!$D$5:$D$517,$B11,'قائمة الوظائف'!$J$5:$J$517,"من واقع الخبرة") -> 0 | I11: =COUNTIFS('قائمة الوظائف'!$D$5:$D$517,$B11,'قائمة الوظائف'!$M$5:$M$517,"نعم") -> 11 | J11: =COUNTIFS('قائمة الوظائف'!$D$5:$D$517,$B11,'قائمة الوظائف'!$L$5:$L$517,"يعمل تشغيلياً") -> 11
A12: إدارة الموارد البشرية والخدمات | B12: الخدمة الذاتية وتطبيق الجوال | C12: Employee Self-Service & Mobile App | D12: وحدة غير واردة في المخطط | E12: =COUNTIFS('قائمة الوظائف'!$D$5:$D$517,$B12) -> 7 | F12: =COUNTIFS('قائمة الوظائف'!$D$5:$D$517,$B12,'قائمة الوظائف'!$J$5:$J$517,"المخطط التفصيلي") -> 0 | G12: =COUNTIFS('قائمة الوظائف'!$D$5:$D$517,$B12,'قائمة الوظائف'!$J$5:$J$517,"قائمة وظائف المورّد") -> 7 | H12: =COUNTIFS('قائمة الوظائف'!$D$5:$D$517,$B12,'قائمة الوظائف'!$J$5:$J$517,"من واقع الخبرة") -> 0 | I12: =COUNTIFS('قائمة الوظائف'!$D$5:$D$517,$B12,'قائمة الوظائف'!$M$5:$M$517,"نعم") -> 7 | J12: =COUNTIFS('قائمة الوظائف'!$D$5:$D$517,$B12,'قائمة الوظائف'!$L$5:$L$517,"يعمل تشغيلياً") -> 7
A13: إدارة الموارد البشرية والخدمات | B13: المشتريات | C13: Purchasing | E13: =COUNTIFS('قائمة الوظائف'!$D$5:$D$517,$B13) -> 30 | F13: =COUNTIFS('قائمة الوظائف'!$D$5:$D$517,$B13,'قائمة الوظائف'!$J$5:$J$517,"المخطط التفصيلي") -> 15 | G13: =COUNTIFS('قائمة الوظائف'!$D$5:$D$517,$B13,'قائمة الوظائف'!$J$5:$J$517,"قائمة وظائف المورّد") -> 6 | H13: =COUNTIFS('قائمة الوظائف'!$D$5:$D$517,$B13,'قائمة الوظائف'!$J$5:$J$517,"من واقع الخبرة") -> 9 | I13: =COUNTIFS('قائمة الوظائف'!$D$5:$D$517,$B13,'قائمة الوظائف'!$M$5:$M$517,"نعم") -> 21 | J13: =COUNTIFS('قائمة الوظائف'!$D$5:$D$517,$B13,'قائمة الوظائف'!$L$5:$L$517,"يعمل تشغيلياً") -> 1
A14: إدارة الموارد البشرية والخدمات | B14: المخازن | C14: Inventory / Stores | E14: =COUNTIFS('قائمة الوظائف'!$D$5:$D$517,$B14) -> 29 | F14: =COUNTIFS('قائمة الوظائف'!$D$5:$D$517,$B14,'قائمة الوظائف'!$J$5:$J$517,"المخطط التفصيلي") -> 15 | G14: =COUNTIFS('قائمة الوظائف'!$D$5:$D$517,$B14,'قائمة الوظائف'!$J$5:$J$517,"قائمة وظائف المورّد") -> 7 | H14: =COUNTIFS('قائمة الوظائف'!$D$5:$D$517,$B14,'قائمة الوظائف'!$J$5:$J$517,"من واقع الخبرة") -> 7 | I14: =COUNTIFS('قائمة الوظائف'!$D$5:$D$517,$B14,'قائمة الوظائف'!$M$5:$M$517,"نعم") -> 22 | J14: =COUNTIFS('قائمة الوظائف'!$D$5:$D$517,$B14,'قائمة الوظائف'!$L$5:$L$517,"يعمل تشغيلياً") -> 6
A15: إدارة الموارد البشرية والخدمات | B15: التدريب والتطوير | C15: Training & Development | D15: الملحق V1.2 · 2026.09.12 · تقلّص النطاق | E15: =COUNTIFS('قائمة الوظائف'!$D$5:$D$517,$B15) -> 31 | F15: =COUNTIFS('قائمة الوظائف'!$D$5:$D$517,$B15,'قائمة الوظائف'!$J$5:$J$517,"المخطط التفصيلي") -> 21 | G15: =COUNTIFS('قائمة الوظائف'!$D$5:$D$517,$B15,'قائمة الوظائف'!$J$5:$J$517,"قائمة وظائف المورّد") -> 0 | H15: =COUNTIFS('قائمة الوظائف'!$D$5:$D$517,$B15,'قائمة الوظائف'!$J$5:$J$517,"من واقع الخبرة") -> 10 | I15: =COUNTIFS('قائمة الوظائف'!$D$5:$D$517,$B15,'قائمة الوظائف'!$M$5:$M$517,"نعم") -> 21 | J15: =COUNTIFS('قائمة الوظائف'!$D$5:$D$517,$B15,'قائمة الوظائف'!$L$5:$L$517,"يعمل تشغيلياً") -> 0
A16: إدارة الموارد البشرية والخدمات | B16: الرعاية الصحية | C16: Healthcare | D16: الملحق V1.2 · 2026.09.12 | E16: =COUNTIFS('قائمة الوظائف'!$D$5:$D$517,$B16) -> 31 | F16: =COUNTIFS('قائمة الوظائف'!$D$5:$D$517,$B16,'قائمة الوظائف'!$J$5:$J$517,"المخطط التفصيلي") -> 20 | G16: =COUNTIFS('قائمة الوظائف'!$D$5:$D$517,$B16,'قائمة الوظائف'!$J$5:$J$517,"قائمة وظائف المورّد") -> 0 | H16: =COUNTIFS('قائمة الوظائف'!$D$5:$D$517,$B16,'قائمة الوظائف'!$J$5:$J$517,"من واقع الخبرة") -> 11 | I16: =COUNTIFS('قائمة الوظائف'!$D$5:$D$517,$B16,'قائمة الوظائف'!$M$5:$M$517,"نعم") -> 20 | J16: =COUNTIFS('قائمة الوظائف'!$D$5:$D$517,$B16,'قائمة الوظائف'!$L$5:$L$517,"يعمل تشغيلياً") -> 0
A17: إدارة الموارد البشرية والخدمات | B17: إدارة المستندات والمراسلات | C17: Documents & Correspondence | D17: الملحق V1.0 · 2026.09.20 · تقلّص النطاق | E17: =COUNTIFS('قائمة الوظائف'!$D$5:$D$517,$B17) -> 26 | F17: =COUNTIFS('قائمة الوظائف'!$D$5:$D$517,$B17,'قائمة الوظائف'!$J$5:$J$517,"المخطط التفصيلي") -> 13 | G17: =COUNTIFS('قائمة الوظائف'!$D$5:$D$517,$B17,'قائمة الوظائف'!$J$5:$J$517,"قائمة وظائف المورّد") -> 0 | H17: =COUNTIFS('قائمة الوظائف'!$D$5:$D$517,$B17,'قائمة الوظائف'!$J$5:$J$517,"من واقع الخبرة") -> 13 | I17: =COUNTIFS('قائمة الوظائف'!$D$5:$D$517,$B17,'قائمة الوظائف'!$M$5:$M$517,"نعم") -> 13 | J17: =COUNTIFS('قائمة الوظائف'!$D$5:$D$517,$B17,'قائمة الوظائف'!$L$5:$L$517,"يعمل تشغيلياً") -> 0
A18: إدارة الموارد البشرية والخدمات | B18: إدارة المركبات | C18: Fleet Management | D18: الملحق V1.1 · 2026.09.12 · تقلّص النطاق | E18: =COUNTIFS('قائمة الوظائف'!$D$5:$D$517,$B18) -> 27 | F18: =COUNTIFS('قائمة الوظائف'!$D$5:$D$517,$B18,'قائمة الوظائف'!$J$5:$J$517,"المخطط التفصيلي") -> 15 | G18: =COUNTIFS('قائمة الوظائف'!$D$5:$D$517,$B18,'قائمة الوظائف'!$J$5:$J$517,"قائمة وظائف المورّد") -> 0 | H18: =COUNTIFS('قائمة الوظائف'!$D$5:$D$517,$B18,'قائمة الوظائف'!$J$5:$J$517,"من واقع الخبرة") -> 12 | I18: =COUNTIFS('قائمة الوظائف'!$D$5:$D$517,$B18,'قائمة الوظائف'!$M$5:$M$517,"نعم") -> 15 | J18: =COUNTIFS('قائمة الوظائف'!$D$5:$D$517,$B18,'قائمة الوظائف'!$L$5:$L$517,"يعمل تشغيلياً") -> 0
A19: إجمالي الموارد البشرية | B19: 14 تطبيق | E19: =SUM(E5:E18) -> 341 | F19: =SUM(F5:F18) -> 172 | G19: =SUM(G5:G18) -> 83 | H19: =SUM(H5:H18) -> 86 | I19: =SUM(I5:I18) -> 255 | J19: =SUM(J5:J18) -> 69
A20: الإدارة المالية | B20: المحاسبة | C20: Accounting | E20: =COUNTIFS('قائمة الوظائف'!$D$5:$D$517,$B20) -> 15 | F20: =COUNTIFS('قائمة الوظائف'!$D$5:$D$517,$B20,'قائمة الوظائف'!$J$5:$J$517,"المخطط التفصيلي") -> 7 | G20: =COUNTIFS('قائمة الوظائف'!$D$5:$D$517,$B20,'قائمة الوظائف'!$J$5:$J$517,"قائمة وظائف المورّد") -> 4 | H20: =COUNTIFS('قائمة الوظائف'!$D$5:$D$517,$B20,'قائمة الوظائف'!$J$5:$J$517,"من واقع الخبرة") -> 4 | I20: =COUNTIFS('قائمة الوظائف'!$D$5:$D$517,$B20,'قائمة الوظائف'!$M$5:$M$517,"نعم") -> 11 | J20: =COUNTIFS('قائمة الوظائف'!$D$5:$D$517,$B20,'قائمة الوظائف'!$L$5:$L$517,"يعمل تشغيلياً") -> 4
A21: الإدارة المالية | B21: المدفوعات | C21: Payments | E21: =COUNTIFS('قائمة الوظائف'!$D$5:$D$517,$B21) -> 19 | F21: =COUNTIFS('قائمة الوظائف'!$D$5:$D$517,$B21,'قائمة الوظائف'!$J$5:$J$517,"المخطط التفصيلي") -> 10 | G21: =COUNTIFS('قائمة الوظائف'!$D$5:$D$517,$B21,'قائمة الوظائف'!$J$5:$J$517,"قائمة وظائف المورّد") -> 5 | H21: =COUNTIFS('قائمة الوظائف'!$D$5:$D$517,$B21,'قائمة الوظائف'!$J$5:$J$517,"من واقع الخبرة") -> 4 | I21: =COUNTIFS('قائمة الوظائف'!$D$5:$D$517,$B21,'قائمة الوظائف'!$M$5:$M$517,"نعم") -> 15 | J21: =COUNTIFS('قائمة الوظائف'!$D$5:$D$517,$B21,'قائمة الوظائف'!$L$5:$L$517,"يعمل تشغيلياً") -> 2
A22: الإدارة المالية | B22: المقبوضات | C22: Receipts | E22: =COUNTIFS('قائمة الوظائف'!$D$5:$D$517,$B22) -> 14 | F22: =COUNTIFS('قائمة الوظائف'!$D$5:$D$517,$B22,'قائمة الوظائف'!$J$5:$J$517,"المخطط التفصيلي") -> 7 | G22: =COUNTIFS('قائمة الوظائف'!$D$5:$D$517,$B22,'قائمة الوظائف'!$J$5:$J$517,"قائمة وظائف المورّد") -> 4 | H22: =COUNTIFS('قائمة الوظائف'!$D$5:$D$517,$B22,'قائمة الوظائف'!$J$5:$J$517,"من واقع الخبرة") -> 3 | I22: =COUNTIFS('قائمة الوظائف'!$D$5:$D$517,$B22,'قائمة الوظائف'!$M$5:$M$517,"نعم") -> 11 | J22: =COUNTIFS('قائمة الوظائف'!$D$5:$D$517,$B22,'قائمة الوظائف'!$L$5:$L$517,"يعمل تشغيلياً") -> 2
A23: الإدارة المالية | B23: الأصول الثابتة | C23: Fixed Assets | E23: =COUNTIFS('قائمة الوظائف'!$D$5:$D$517,$B23) -> 11 | F23: =COUNTIFS('قائمة الوظائف'!$D$5:$D$517,$B23,'قائمة الوظائف'!$J$5:$J$517,"المخطط التفصيلي") -> 4 | G23: =COUNTIFS('قائمة الوظائف'!$D$5:$D$517,$B23,'قائمة الوظائف'!$J$5:$J$517,"قائمة وظائف المورّد") -> 1 | H23: =COUNTIFS('قائمة الوظائف'!$D$5:$D$517,$B23,'قائمة الوظائف'!$J$5:$J$517,"من واقع الخبرة") -> 6 | I23: =COUNTIFS('قائمة الوظائف'!$D$5:$D$517,$B23,'قائمة الوظائف'!$M$5:$M$517,"نعم") -> 5 | J23: =COUNTIFS('قائمة الوظائف'!$D$5:$D$517,$B23,'قائمة الوظائف'!$L$5:$L$517,"يعمل تشغيلياً") -> 1
A24: الإدارة المالية | B24: الاعتمادات المستندية | C24: Letters of Credit | D24: وحدة غير واردة في المخطط | E24: =COUNTIFS('قائمة الوظائف'!$D$5:$D$517,$B24) -> 7 | F24: =COUNTIFS('قائمة الوظائف'!$D$5:$D$517,$B24,'قائمة الوظائف'!$J$5:$J$517,"المخطط التفصيلي") -> 0 | G24: =COUNTIFS('قائمة الوظائف'!$D$5:$D$517,$B24,'قائمة الوظائف'!$J$5:$J$517,"قائمة وظائف المورّد") -> 7 | H24: =COUNTIFS('قائمة الوظائف'!$D$5:$D$517,$B24,'قائمة الوظائف'!$J$5:$J$517,"من واقع الخبرة") -> 0 | I24: =COUNTIFS('قائمة الوظائف'!$D$5:$D$517,$B24,'قائمة الوظائف'!$M$5:$M$517,"نعم") -> 7 | J24: =COUNTIFS('قائمة الوظائف'!$D$5:$D$517,$B24,'قائمة الوظائف'!$L$5:$L$517,"يعمل تشغيلياً") -> 4
A25: الإدارة المالية | B25: دورة حياة العقود | C25: Contract Lifecycle | E25: =COUNTIFS('قائمة الوظائف'!$D$5:$D$517,$B25) -> 18 | F25: =COUNTIFS('قائمة الوظائف'!$D$5:$D$517,$B25,'قائمة الوظائف'!$J$5:$J$517,"المخطط التفصيلي") -> 9 | G25: =COUNTIFS('قائمة الوظائف'!$D$5:$D$517,$B25,'قائمة الوظائف'!$J$5:$J$517,"قائمة وظائف المورّد") -> 1 | H25: =COUNTIFS('قائمة الوظائف'!$D$5:$D$517,$B25,'قائمة الوظائف'!$J$5:$J$517,"من واقع الخبرة") -> 8 | I25: =COUNTIFS('قائمة الوظائف'!$D$5:$D$517,$B25,'قائمة الوظائف'!$M$5:$M$517,"نعم") -> 10 | J25: =COUNTIFS('قائمة الوظائف'!$D$5:$D$517,$B25,'قائمة الوظائف'!$L$5:$L$517,"يعمل تشغيلياً") -> 0
A26: إجمالي المالية | B26: 6 تطبيق | E26: =SUM(E20:E25) -> 84 | F26: =SUM(F20:F25) -> 37 | G26: =SUM(G20:G25) -> 22 | H26: =SUM(H20:H25) -> 25 | I26: =SUM(I20:I25) -> 59 | J26: =SUM(J20:J25) -> 13
A27: الإدارة التجارية | B27: المبيعات | C27: Sales | E27: =COUNTIFS('قائمة الوظائف'!$D$5:$D$517,$B27) -> 21 | F27: =COUNTIFS('قائمة الوظائف'!$D$5:$D$517,$B27,'قائمة الوظائف'!$J$5:$J$517,"المخطط التفصيلي") -> 10 | G27: =COUNTIFS('قائمة الوظائف'!$D$5:$D$517,$B27,'قائمة الوظائف'!$J$5:$J$517,"قائمة وظائف المورّد") -> 7 | H27: =COUNTIFS('قائمة الوظائف'!$D$5:$D$517,$B27,'قائمة الوظائف'!$J$5:$J$517,"من واقع الخبرة") -> 4 | I27: =COUNTIFS('قائمة الوظائف'!$D$5:$D$517,$B27,'قائمة الوظائف'!$M$5:$M$517,"نعم") -> 17 | J27: =COUNTIFS('قائمة الوظائف'!$D$5:$D$517,$B27,'قائمة الوظائف'!$L$5:$L$517,"يعمل تشغيلياً") -> 2
A28: الإدارة التجارية | B28: خدمات المشتركين | C28: Subscriber Services | E28: =COUNTIFS('قائمة الوظائف'!$D$5:$D$517,$B28) -> 3 | F28: =COUNTIFS('قائمة الوظائف'!$D$5:$D$517,$B28,'قائمة الوظائف'!$J$5:$J$517,"المخطط التفصيلي") -> 0 | G28: =COUNTIFS('قائمة الوظائف'!$D$5:$D$517,$B28,'قائمة الوظائف'!$J$5:$J$517,"قائمة وظائف المورّد") -> 1 | H28: =COUNTIFS('قائمة الوظائف'!$D$5:$D$517,$B28,'قائمة الوظائف'!$J$5:$J$517,"من واقع الخبرة") -> 2 | I28: =COUNTIFS('قائمة الوظائف'!$D$5:$D$517,$B28,'قائمة الوظائف'!$M$5:$M$517,"نعم") -> 1 | J28: =COUNTIFS('قائمة الوظائف'!$D$5:$D$517,$B28,'قائمة الوظائف'!$L$5:$L$517,"يعمل تشغيلياً") -> 0
A29: إجمالي التجارية | B29: 2 تطبيق | E29: =SUM(E27:E28) -> 24 | F29: =SUM(F27:F28) -> 10 | G29: =SUM(G27:G28) -> 8 | H29: =SUM(H27:H28) -> 6 | I29: =SUM(I27:I28) -> 18 | J29: =SUM(J27:J28) -> 2
A30: التهيئة والبنية التحتية والمتطلبات | B30: الخوادم والتخزين | C30: Servers & Storage | E30: =COUNTIFS('قائمة الوظائف'!$D$5:$D$517,$B30) -> 8 | F30: =COUNTIFS('قائمة الوظائف'!$D$5:$D$517,$B30,'قائمة الوظائف'!$J$5:$J$517,"المخطط التفصيلي") -> 3 | G30: =COUNTIFS('قائمة الوظائف'!$D$5:$D$517,$B30,'قائمة الوظائف'!$J$5:$J$517,"قائمة وظائف المورّد") -> 1 | H30: =COUNTIFS('قائمة الوظائف'!$D$5:$D$517,$B30,'قائمة الوظائف'!$J$5:$J$517,"من واقع الخبرة") -> 4 | I30: =COUNTIFS('قائمة الوظائف'!$D$5:$D$517,$B30,'قائمة الوظائف'!$M$5:$M$517,"نعم") -> 4 | J30: =COUNTIFS('قائمة الوظائف'!$D$5:$D$517,$B30,'قائمة الوظائف'!$L$5:$L$517,"يعمل تشغيلياً") -> 1
A31: التهيئة والبنية التحتية والمتطلبات | B31: قاعدة البيانات والتراخيص | C31: Database & Licences | E31: =COUNTIFS('قائمة الوظائف'!$D$5:$D$517,$B31) -> 8 | F31: =COUNTIFS('قائمة الوظائف'!$D$5:$D$517,$B31,'قائمة الوظائف'!$J$5:$J$517,"المخطط التفصيلي") -> 2 | G31: =COUNTIFS('قائمة الوظائف'!$D$5:$D$517,$B31,'قائمة الوظائف'!$J$5:$J$517,"قائمة وظائف المورّد") -> 1 | H31: =COUNTIFS('قائمة الوظائف'!$D$5:$D$517,$B31,'قائمة الوظائف'!$J$5:$J$517,"من واقع الخبرة") -> 5 | I31: =COUNTIFS('قائمة الوظائف'!$D$5:$D$517,$B31,'قائمة الوظائف'!$M$5:$M$517,"نعم") -> 3 | J31: =COUNTIFS('قائمة الوظائف'!$D$5:$D$517,$B31,'قائمة الوظائف'!$L$5:$L$517,"يعمل تشغيلياً") -> 1
A32: التهيئة والبنية التحتية والمتطلبات | B32: الشبكة والربط بالفروع | C32: Network & Branch Connectivity | E32: =COUNTIFS('قائمة الوظائف'!$D$5:$D$517,$B32) -> 9 | F32: =COUNTIFS('قائمة الوظائف'!$D$5:$D$517,$B32,'قائمة الوظائف'!$J$5:$J$517,"المخطط التفصيلي") -> 2 | G32: =COUNTIFS('قائمة الوظائف'!$D$5:$D$517,$B32,'قائمة الوظائف'!$J$5:$J$517,"قائمة وظائف المورّد") -> 2 | H32: =COUNTIFS('قائمة الوظائف'!$D$5:$D$517,$B32,'قائمة الوظائف'!$J$5:$J$517,"من واقع الخبرة") -> 5 | I32: =COUNTIFS('قائمة الوظائف'!$D$5:$D$517,$B32,'قائمة الوظائف'!$M$5:$M$517,"نعم") -> 4 | J32: =COUNTIFS('قائمة الوظائف'!$D$5:$D$517,$B32,'قائمة الوظائف'!$L$5:$L$517,"يعمل تشغيلياً") -> 2
A33: التهيئة والبنية التحتية والمتطلبات | B33: بيئات العمل والنشر | C33: Environments & Deployment | E33: =COUNTIFS('قائمة الوظائف'!$D$5:$D$517,$B33) -> 6 | F33: =COUNTIFS('قائمة الوظائف'!$D$5:$D$517,$B33,'قائمة الوظائف'!$J$5:$J$517,"المخطط التفصيلي") -> 0 | G33: =COUNTIFS('قائمة الوظائف'!$D$5:$D$517,$B33,'قائمة الوظائف'!$J$5:$J$517,"قائمة وظائف المورّد") -> 2 | H33: =COUNTIFS('قائمة الوظائف'!$D$5:$D$517,$B33,'قائمة الوظائف'!$J$5:$J$517,"من واقع الخبرة") -> 4 | I33: =COUNTIFS('قائمة الوظائف'!$D$5:$D$517,$B33,'قائمة الوظائف'!$M$5:$M$517,"نعم") -> 2 | J33: =COUNTIFS('قائمة الوظائف'!$D$5:$D$517,$B33,'قائمة الوظائف'!$L$5:$L$517,"يعمل تشغيلياً") -> 2
A34: التهيئة والبنية التحتية والمتطلبات | B34: النسخ الاحتياطي والتعافي | C34: Backup & Recovery | E34: =COUNTIFS('قائمة الوظائف'!$D$5:$D$517,$B34) -> 5 | F34: =COUNTIFS('قائمة الوظائف'!$D$5:$D$517,$B34,'قائمة الوظائف'!$J$5:$J$517,"المخطط التفصيلي") -> 0 | G34: =COUNTIFS('قائمة الوظائف'!$D$5:$D$517,$B34,'قائمة الوظائف'!$J$5:$J$517,"قائمة وظائف المورّد") -> 1 | H34: =COUNTIFS('قائمة الوظائف'!$D$5:$D$517,$B34,'قائمة الوظائف'!$J$5:$J$517,"من واقع الخبرة") -> 4 | I34: =COUNTIFS('قائمة الوظائف'!$D$5:$D$517,$B34,'قائمة الوظائف'!$M$5:$M$517,"نعم") -> 1 | J34: =COUNTIFS('قائمة الوظائف'!$D$5:$D$517,$B34,'قائمة الوظائف'!$L$5:$L$517,"يعمل تشغيلياً") -> 1
A35: التهيئة والبنية التحتية والمتطلبات | B35: الأمن والصلاحيات والتسليم | C35: Security, Permissions & Handover | E35: =COUNTIFS('قائمة الوظائف'!$D$5:$D$517,$B35) -> 10 | F35: =COUNTIFS('قائمة الوظائف'!$D$5:$D$517,$B35,'قائمة الوظائف'!$J$5:$J$517,"المخطط التفصيلي") -> 2 | G35: =COUNTIFS('قائمة الوظائف'!$D$5:$D$517,$B35,'قائمة الوظائف'!$J$5:$J$517,"قائمة وظائف المورّد") -> 4 | H35: =COUNTIFS('قائمة الوظائف'!$D$5:$D$517,$B35,'قائمة الوظائف'!$J$5:$J$517,"من واقع الخبرة") -> 4 | I35: =COUNTIFS('قائمة الوظائف'!$D$5:$D$517,$B35,'قائمة الوظائف'!$M$5:$M$517,"نعم") -> 6 | J35: =COUNTIFS('قائمة الوظائف'!$D$5:$D$517,$B35,'قائمة الوظائف'!$L$5:$L$517,"يعمل تشغيلياً") -> 2
A36: التهيئة والبنية التحتية والمتطلبات | B36: ترحيل البيانات | C36: Data Migration | E36: =COUNTIFS('قائمة الوظائف'!$D$5:$D$517,$B36) -> 10 | F36: =COUNTIFS('قائمة الوظائف'!$D$5:$D$517,$B36,'قائمة الوظائف'!$J$5:$J$517,"المخطط التفصيلي") -> 2 | G36: =COUNTIFS('قائمة الوظائف'!$D$5:$D$517,$B36,'قائمة الوظائف'!$J$5:$J$517,"قائمة وظائف المورّد") -> 1 | H36: =COUNTIFS('قائمة الوظائف'!$D$5:$D$517,$B36,'قائمة الوظائف'!$J$5:$J$517,"من واقع الخبرة") -> 7 | I36: =COUNTIFS('قائمة الوظائف'!$D$5:$D$517,$B36,'قائمة الوظائف'!$M$5:$M$517,"نعم") -> 3 | J36: =COUNTIFS('قائمة الوظائف'!$D$5:$D$517,$B36,'قائمة الوظائف'!$L$5:$L$517,"يعمل تشغيلياً") -> 1
A37: التهيئة والبنية التحتية والمتطلبات | B37: التدريب ونقل المعرفة | C37: Training & Knowledge Transfer | E37: =COUNTIFS('قائمة الوظائف'!$D$5:$D$517,$B37) -> 8 | F37: =COUNTIFS('قائمة الوظائف'!$D$5:$D$517,$B37,'قائمة الوظائف'!$J$5:$J$517,"المخطط التفصيلي") -> 2 | G37: =COUNTIFS('قائمة الوظائف'!$D$5:$D$517,$B37,'قائمة الوظائف'!$J$5:$J$517,"قائمة وظائف المورّد") -> 0 | H37: =COUNTIFS('قائمة الوظائف'!$D$5:$D$517,$B37,'قائمة الوظائف'!$J$5:$J$517,"من واقع الخبرة") -> 6 | I37: =COUNTIFS('قائمة الوظائف'!$D$5:$D$517,$B37,'قائمة الوظائف'!$M$5:$M$517,"نعم") -> 2 | J37: =COUNTIFS('قائمة الوظائف'!$D$5:$D$517,$B37,'قائمة الوظائف'!$L$5:$L$517,"يعمل تشغيلياً") -> 0
A38: إجمالي البنية التحتية | B38: 8 تطبيق | E38: =SUM(E30:E37) -> 64 | F38: =SUM(F30:F37) -> 13 | G38: =SUM(G30:G37) -> 12 | H38: =SUM(H30:H37) -> 39 | I38: =SUM(I30:I37) -> 25 | J38: =SUM(J30:J37) -> 10
A39: الإجمالي العام | B39: 30 تطبيق | E39: =E19+E26+E29+E38 -> 513 | F39: =F19+F26+F29+F38 -> 232 | G39: =G19+G26+G29+G38 -> 125 | H39: =H19+H26+H29+H38 -> 156 | I39: =I19+I26+I29+I38 -> 357 | J39: =J19+J26+J29+J38 -> 94
A41: تحقق: عدد صفوف القائمة | E41: =COUNTA('قائمة الوظائف'!$H$5:$H$517) -> 513 | F41: =IF(E41=E39,"مطابق","غير مطابق") -> مطابق

Sheet قائمة الوظائف
A1: قائمة الوظائف الكاملة حسب الموديول (الإدارة) والتطبيق — نظام متابعة إنجاز ERP
A2: المصدر: كتالوج النظام (backend/src/db/seed/catalog.json) المستخرج من ملف المتابعة الأصلي erp-tracker-original.html — مطابق له 100%. لا تشمل الوظائف المضافة أو المُزالة لاحقاً على الخادم.
A4: م | B4: الموديول (الإدارة) | C4: Module | D4: التطبيق | E4: Application | F4: رمز التطبيق | G4: تابع لـ / ملاحظات التطبيق | H4: رمز الوظيفة | I4: اسم الوظيفة | J4: المصدر | K4: المرجع | L4: حالة المورّد المعلنة | M4: محسوبة في النسب افتراضياً
A5: 1 | B5: إدارة الموارد البشرية والخدمات | C5: Human Resources & Services | D5: شؤون العاملين | E5: Personnel Affairs | F5: per | H5: D0 | I5: الوظائف والدرجة الوظيفية وفترة الاختبار | J5: المخطط التفصيلي | K5: ص 69 | L5: — | M5: نعم
A6: 2 | B6: إدارة الموارد البشرية والخدمات | C6: Human Resources & Services | D6: شؤون العاملين | E6: Personnel Affairs | F6: per | H6: D1 | I6: المواقع الوظيفية ومقارنة الخطة بالتوظيف الفعلي | J6: المخطط التفصيلي | K6: ص 69 | L6: — | M6: نعم
A7: 3 | B7: إدارة الموارد البشرية والخدمات | C7: Human Resources & Services | D7: شؤون العاملين | E7: Personnel Affairs | F7: per | H7: D2 | I7: الهيكل الإداري والوظيفي الديناميكي وربط الموظف بالوظيفة الإشرافية | J7: المخطط التفصيلي | K7: ص 92 | L7: — | M7: نعم
A8: 4 | B8: إدارة الموارد البشرية والخدمات | C8: Human Resources & Services | D8: شؤون العاملين | E8: Personnel Affairs | F8: per | H8: D3 | I8: البيانات الشخصية: الاسم، المؤهل، الجنس، الرقم الوطني، الميلاد، الحالة الاجتماعية، الهواتف، الرقم الضماني، جواز السفر، العنوان بإحداثيات | J8: المخطط التفصيلي | K8: ص 92 | L8: — | M8: نعم
A9: 5 | B9: إدارة الموارد البشرية والخدمات | C9: Human Resources & Services | D9: شؤون العاملين | E9: Personnel Affairs | F9: per | H9: D4 | I9: عقد العمل: تاريخ التعيين والوظيفة والمرتب، الإصدار الآلي للعقود، النقل بين الإدارات | J9: المخطط التفصيلي | K9: ص 92 | L9: — | M9: نعم
A10: 6 | B10: إدارة الموارد البشرية والخدمات | C10: Human Resources & Services | D10: شؤون العاملين | E10: Personnel Affairs | F10: per | H10: D5 | I10: مسوغات التعيين حسب الوظيفة والجنس والجنسية | J10: المخطط التفصيلي | K10: ص 92 | L10: — | M10: نعم
A11: 7 | B11: إدارة الموارد البشرية والخدمات | C11: Human Resources & Services | D11: شؤون العاملين | E11: Personnel Affairs | F11: per | H11: D6 | I11: أمر تكليف العمل | J11: المخطط التفصيلي | K11: ص 92 | L11: — | M11: نعم
A12: 8 | B12: إدارة الموارد البشرية والخدمات | C12: Human Resources & Services | D12: شؤون العاملين | E12: Personnel Affairs | F12: per | H12: D7 | I12: أرشفة بيانات الموظف وتعريف بصمته | J12: المخطط التفصيلي | K12: ص 64 | L12: — | M12: نعم
A13: 9 | B13: إدارة الموارد البشرية والخدمات | C13: Human Resources & Services | D13: شؤون العاملين | E13: Personnel Affairs | F13: per | H13: D8 | I13: دليل جهات التعامل للمأموريات والاجتماعات بموقع GPS | J13: المخطط التفصيلي | K13: ص 92 | L13: — | M13: نعم
A14: 10 | B14: إدارة الموارد البشرية والخدمات | C14: Human Resources & Services | D14: شؤون العاملين | E14: Personnel Affairs | F14: per | H14: D9 | I14: قوالب خطابات شؤون العاملين وتصنيفها في مجلدات | J14: المخطط التفصيلي | K14: ص 93 | L14: — | M14: نعم
A15: 11 | B15: إدارة الموارد البشرية والخدمات | C15: Human Resources & Services | D15: شؤون العاملين | E15: Personnel Affairs | F15: per | H15: D10 | I15: طلب خطاب شؤون عاملين عبر الخدمة الذاتية | J15: المخطط التفصيلي | K15: ص 93 | L15: — | M15: نعم
A16: 12 | B16: إدارة الموارد البشرية والخدمات | C16: Human Resources & Services | D16: شؤون العاملين | E16: Personnel Affairs | F16: per | H16: D11 | I16: العهد العينية والمالية: التصنيف، الرقم المسلسل، الحالة، تاريخ الشراء، المكان، آلية الصرف وإقرار الاستلام، الاستيراد من إكسيل | J16: المخطط التفصيلي | K16: ص 93 و95 | L16: — | M16: نعم
... A44: 40 | B44: إدارة الموارد البشرية والخدمات | C44: Human Resources & Services | D44: شؤون العاملين | E44: Personnel Affairs | F44: per | H44: X6 | I44: رقم اشتراك الضمان الاجتماعي وحالته | J44: من واقع الخبرة | K44: الوثيقة تحفظ «الرقم الضماني» كحقل فقط دون دورة اشتراك | L44: — | M44: لا (مقترح)
A45: 41 | B45: إدارة الموارد البشرية والخدمات | C45: Human Resources & Services | D45: التوظيف | E45: Recruitment | F45: rec | G45: ضمن شؤون العاملين | H45: D0 | I45: إعدادات التوظيف: حقول استمارة التوظيف وأسئلة التقييم | J45: المخطط التفصيلي | K45: ص 69 | L45: — | M45: نعم
A46: 42 | B46: إدارة الموارد البشرية والخدمات | C46: Human Resources & Services | D46: التوظيف | E46: Recruitment | F46: rec | G46: ضمن شؤون العاملين | H46: D1 | I46: مسارات اعتماد طلبات التوظيف | J46: المخطط التفصيلي | K46: ص 69 | L46: — | M46: نعم
A47: 43 | B47: إدارة الموارد البشرية والخدمات | C47: Human Resources & Services | D47: التوظيف | E47: Recruitment | F47: rec | G47: ضمن شؤون العاملين | H47: D2 | I47: طلب التوظيف من الإدارة الطالبة: المدير، التاريخ، العدد، المهارات | J47: المخطط التفصيلي | K47: ص 69 | L47: — | M47: نعم
A48: 44 | B48: إدارة الموارد البشرية والخدمات | C48: Human Resources & Services | D48: التوظيف | E48: Recruitment | F48: rec | G48: ضمن شؤون العاملين | H48: D3 | I48: تجميع طلبات التوظيف وإنشاء إعلانات منها | J48: المخطط التفصيلي | K48: ص 69 | L48: — | M48: نعم
A49: 45 | B49: إدارة الموارد البشرية والخدمات | C49: Human Resources & Services | D49: التوظيف | E49: Recruitment | F49: rec | G49: ضمن شؤون العاملين | H49: D4 | I49: نشر الإعلانات على منصات التوظيف ومتابعة المنشور والسابق | J49: المخطط التفصيلي | K49: ص 69 و64 | L49: — | M49: نعم
A50: 46 | B50: إدارة الموارد البشرية والخدمات | C50: Human Resources & Services | D50: التوظيف | E50: Recruitment | F50: rec | G50: ضمن شؤون العاملين | H50: D5 | I50: استمارات المتقدمين لكل وظيفة | J50: المخطط التفصيلي | K50: ص 69 | L50: — | M50: نعم
A51: 47 | B51: إدارة الموارد البشرية والخدمات | C51: Human Resources & Services | D51: التوظيف | E51: Recruitment | F51: rec | G51: ضمن شؤون العاملين | H51: D6 | I51: تصنيف المتقدمين مطابق/غير مطابق بالذكاء الاصطناعي | J51: المخطط التفصيلي | K51: ص 69 و64 | L51: — | M51: نعم
A52: 48 | B52: إدارة الموارد البشرية والخدمات | C52: Human Resources & Services | D52: التوظيف | E52: Recruitment | F52: rec | G52: ضمن شؤون العاملين | H52: D7 | I52: تقييم المتقدمين من لجنة التوظيف | J52: المخطط التفصيلي | K52: ص 69 | L52: — | M52: نعم
A53: 49 | B53: إدارة الموارد البشرية والخدمات | C53: Human Resources & Services | D53: التوظيف | E53: Recruitment | F53: rec | G53: ضمن شؤون العاملين | H53: D8 | I53: إجراءات التوظيف والتأكد من بيانات المرشحين المقبولين | J53: المخطط التفصيلي | K53: ص 69 | L53: — | M53: نعم
A54: 50 | B54: إدارة الموارد البشرية والخدمات | C54: Human Resources & Services | D54: التوظيف | E54: Recruitment | F54: rec | G54: ضمن شؤون العاملين | H54: D9 | I54: إعداد العرض الوظيفي | J54: المخطط التفصيلي | K54: ص 64 | L54: — | M54: نعم
A55: 51 | B55: إدارة الموارد البشرية والخدمات | C55: Human Resources & Services | D55: التوظيف | E55: Recruitment | F55: rec | G55: ضمن شؤون العاملين | H55: D10 | I55: طلب مسوغات التعيين | J55: المخطط التفصيلي | K55: ص 64 | L55: — | M55: نعم
A56: 52 | B56: إدارة الموارد البشرية والخدمات | C56: Human Resources & Services | D56: التوظيف | E56: Recruitment | F56: rec | G56: ضمن شؤون العاملين | H56: D11 | I56: إعداد الرسالة المباشرة | J56: المخطط التفصيلي | K56: ص 64 | L56: — | M56: نعم
... A59: 55 | B59: إدارة الموارد البشرية والخدمات | C59: Human Resources & Services | D59: التوظيف | E59: Recruitment | F59: rec | G59: ضمن شؤون العاملين | H59: X0 | I59: الملاك المعتمد مقابل الفعلي وربطه بموازنة التوظيف | J59: من واقع الخبرة | K59: المواقع الوظيفية موجودة دون ربطها بسقف مالي، فيمرّ التوظيف دون رقابة ميزانية | L59: — | M59: لا (مقترح)
A60: 56 | B60: إدارة الموارد البشرية والخدمات | C60: Human Resources & Services | D60: الحضور والانصراف | E60: Time & Attendance | F60: att | H60: D0 | I60: ربط أجهزة البصمة ZK وBio star وNitgen وsystem max، وربط أجهزة كل فرع على حدة، والمزامنة التلقائية | J60: المخطط التفصيلي | K60: ص 95 | L60: — | M60: نعم
A61: 57 | B61: إدارة الموارد البشرية والخدمات | C61: Human Resources & Services | D61: الحضور والانصراف | E61: Time & Attendance | F61: att | H61: D1 | I61: جداول الأعمال: يومي، أسبوعي، شهري، سنوي | J61: المخطط التفصيلي | K61: ص 95 | L61: — | M61: نعم
A62: 58 | B62: إدارة الموارد البشرية والخدمات | C62: Human Resources & Services | D62: الحضور والانصراف | E62: Time & Attendance | F62: att | H62: D2 | I62: الورديات النظامية والتناوبية، وإضافة وتعديل وردية بديلة | J62: المخطط التفصيلي | K62: ص 95 | L62: — | M62: نعم
A63: 59 | B63: إدارة الموارد البشرية والخدمات | C63: Human Resources & Services | D63: الحضور والانصراف | E63: Time & Attendance | F63: att | H63: D3 | I63: تعددية فترات السماح ومرونة أوقات الحضور والانصراف | J63: المخطط التفصيلي | K63: ص 95 | L63: — | M63: نعم
A64: 60 | B64: إدارة الموارد البشرية والخدمات | C64: Human Resources & Services | D64: الحضور والانصراف | E64: Time & Attendance | F64: att | H64: D4 | I64: حضور الموقع عبر GPS من تطبيق الهاتف | J64: المخطط التفصيلي | K64: ص 83 | L64: — | M64: نعم
A65: 61 | B65: إدارة الموارد البشرية والخدمات | C65: Human Resources & Services | D65: الحضور والانصراف | E65: Time & Attendance | F65: att | H65: D5 | I65: طلب الالتماس عند نسيان التوقيع | J65: المخطط التفصيلي | K65: عرض فني ص 68 | L65: — | M65: نعم
A66: 62 | B66: إدارة الموارد البشرية والخدمات | C66: Human Resources & Services | D66: الحضور والانصراف | E66: Time & Attendance | F66: att | H66: D6 | I66: سياسة الأذون الخاصة بسقف شهري دون خصم | J66: المخطط التفصيلي | K66: ص 94 | L66: — | M66: نعم
A67: 63 | B67: إدارة الموارد البشرية والخدمات | C67: Human Resources & Services | D67: الحضور والانصراف | E67: Time & Attendance | F67: att | H67: D7 | I67: الوقت الإضافي واحتساب نقاطه | J67: المخطط التفصيلي | K67: ص 96 | L67: — | M67: نعم
A68: 64 | B68: إدارة الموارد البشرية والخدمات | C68: Human Resources & Services | D68: الحضور والانصراف | E68: Time & Attendance | F68: att | H68: D8 | I68: نظام الانقطاع عن العمل: لوائحه ودوريته ومراقبة المتصل والمنفصل | J68: المخطط التفصيلي | K68: ص 95 | L68: — | M68: نعم
A69: 65 | B69: إدارة الموارد البشرية والخدمات | C69: Human Resources & Services | D69: الحضور والانصراف | E69: Time & Attendance | F69: att | H69: D9 | I69: لوائح جزاءات التأخير والغياب وتصاعدها عند التكرار | J69: المخطط التفصيلي | K69: ص 94 | L69: — | M69: نعم
A70: 66 | B70: إدارة الموارد البشرية والخدمات | C70: Human Resources & Services | D70: الحضور والانصراف | E70: Time & Attendance | F70: att | H70: D10 | I70: العطلات الرسمية وحالتها مدفوعة من عدمها وتخصيصها لفروع | J70: المخطط التفصيلي | K70: ص 92 | L70: — | M70: نعم
A71: 67 | B71: إدارة الموارد البشرية والخدمات | C71: Human Resources & Services | D71: الحضور والانصراف | E71: Time & Attendance | F71: att | H71: D11 | I71: داش بورد الموظف والمدير بمتغيرات الشهر | J71: المخطط التفصيلي | K71: ص 98 | L71: — | M71: نعم
... A139: 135 | B139: إدارة الموارد البشرية والخدمات | C139: Human Resources & Services | D139: المرتبات والسلف | E139: Payroll & Advances | F139: pay | H139: X6 | I139: التكلفة الكلية للموظف: المرتب + التأمينات + المزايا | J139: من واقع الخبرة | K139: لتحميلها على المشاريع ومراكز التكلفة بدل المرتب وحده | L139: — | M139: لا (مقترح)
A140: 136 | B140: إدارة الموارد البشرية والخدمات | C140: Human Resources & Services | D140: التقييم | E140: Appraisal | F140: apr | G140: ضمن المرتبات | H140: D0 | I140: دليل معايير التقييم: المظهر، سرعة العمل، اللباقة، المرونة، الغياب | J140: المخطط التفصيلي | K140: ص 93 | L140: — | M140: نعم
A141: 137 | B141: إدارة الموارد البشرية والخدمات | C141: Human Resources & Services | D141: التقييم | E141: Appraisal | F141: apr | G141: ضمن المرتبات | H141: D1 | I141: ربط المعيار بمعادلة تُحتسب تلقائياً مثل الغياب من الحضور والانصراف | J141: المخطط التفصيلي | K141: ص 93 | L141: — | M141: نعم
A142: 138 | B142: إدارة الموارد البشرية والخدمات | C142: Human Resources & Services | D142: التقييم | E142: Appraisal | F142: apr | G142: ضمن المرتبات | H142: D2 | I142: دليل درجات التقييم وتقدير كل درجة | J142: المخطط التفصيلي | K142: ص 93 | L142: — | M142: نعم
A143: 139 | B143: إدارة الموارد البشرية والخدمات | C143: Human Resources & Services | D143: التقييم | E143: Appraisal | F143: apr | G143: ضمن المرتبات | H143: D3 | I143: دليل نماذج التقييم مربوطة بالوظيفة | J143: المخطط التفصيلي | K143: ص 93 | L143: — | M143: نعم
A144: 140 | B144: إدارة الموارد البشرية والخدمات | C144: Human Resources & Services | D144: التقييم | E144: Appraisal | F144: apr | G144: ضمن المرتبات | H144: D4 | I144: خطة التقييم الدورية: شهري، ربع سنوي، نصف سنوي، سنوي | J144: المخطط التفصيلي | K144: ص 95 | L144: — | M144: نعم
A145: 141 | B145: إدارة الموارد البشرية والخدمات | C145: Human Resources & Services | D145: التقييم | E145: Appraisal | F145: apr | G145: ضمن المرتبات | H145: D5 | I145: الفئات المستهدفة لكل خطة ومسار اعتمادها | J145: المخطط التفصيلي | K145: ص 95 | L145: — | M145: نعم
A146: 142 | B146: إدارة الموارد البشرية والخدمات | C146: Human Resources & Services | D146: التقييم | E146: Appraisal | F146: apr | G146: ضمن المرتبات | H146: D6 | I146: طلب تقييم الموظف وإخطاره بالنتيجة | J146: المخطط التفصيلي | K146: عرض فني ص 60 | L146: — | M146: نعم
A147: 143 | B147: إدارة الموارد البشرية والخدمات | C147: Human Resources & Services | D147: التقييم | E147: Appraisal | F147: apr | G147: ضمن المرتبات | H147: D7 | I147: كشف تقييم الأداء وتقارير تحليل المعايير | J147: المخطط التفصيلي | K147: ص 65 و97 | L147: — | M147: نعم
A148: 144 | B148: إدارة الموارد البشرية والخدمات | C148: Human Resources & Services | D148: التقييم | E148: Appraisal | F148: apr | G148: ضمن المرتبات | H148: D8 | I148: عرض تقييمات الأداء الدورية في الخدمة الذاتية | J148: قائمة وظائف المورّد | K148: قائمة الوظائف بند 160 | L148: يعمل مع ملاحظة | M148: نعم
A149: 145 | B149: إدارة الموارد البشرية والخدمات | C149: Human Resources & Services | D149: التقييم | E149: Appraisal | F149: apr | G149: ضمن المرتبات | H149: D9 | I149: تقييمات الموظفين — تعبئة النموذج من المدير | J149: قائمة وظائف المورّد | K149: بند 186 | L149: يعمل تشغيلياً | M149: نعم
A150: 146 | B150: إدارة الموارد البشرية والخدمات | C150: Human Resources & Services | D150: التقييم | E150: Appraisal | F150: apr | G150: ضمن المرتبات | H150: X0 | I150: قاعدة معلنة تربط نتيجة التقييم بالزيادة والترقية | J150: من واقع الخبرة | K150: الباقات تذكر «ربط التقييم بالأجور والمرتبات» دون تحديد القاعدة | L150: — | M150: لا (مقترح)
A151: 147 | B151: إدارة الموارد البشرية والخدمات | C151: Human Resources & Services | D151: التقييم | E151: Appraisal | F151: apr | G151: ضمن المرتبات | H151: X1 | I151: أهداف فردية قابلة للقياس إلى جانب معايير السلوك | J151: من واقع الخبرة | K151: المعايير الخمسة في الوثيقة سلوكية بالكامل ولا تقيس إنجازاً | L151: — | M151: لا (مقترح)
... A171: 167 | B171: إدارة الموارد البشرية والخدمات | C171: Human Resources & Services | D171: الخدمة الذاتية وتطبيق الجوال | E171: Employee Self-Service & Mobile App | F171: ess | G171: وحدة غير واردة في المخطط | H171: D6 | I171: إجراءات يبدأها المدير: طلب توظيف، تكليف مأمورية، توقيع جزاء، إصدار قرار أو تعميم، تقييمات الموظفين | J171: قائمة وظائف المورّد | K171: بند 178–186 | L171: يعمل تشغيلياً | M171: نعم
A172: 168 | B172: إدارة الموارد البشرية والخدمات | C172: Human Resources & Services | D172: المشتريات | E172: Purchasing | F172: pur | H172: D0 | I172: دليل جهات التعامل (الموردين) ودليل المندوبين | J172: المخطط التفصيلي | K172: ص 98 | L172: — | M172: نعم
A173: 169 | B173: إدارة الموارد البشرية والخدمات | C173: Human Resources & Services | D173: المشتريات | E173: Purchasing | F173: pur | H173: D1 | I173: دليل الأصناف السلعية والخدمية والخصومات | J173: المخطط التفصيلي | K173: ص 98 | L173: — | M173: نعم
A174: 170 | B174: إدارة الموارد البشرية والخدمات | C174: Human Resources & Services | D174: المشتريات | E174: Purchasing | F174: pur | H174: D2 | I174: مسارات الاعتماد ودفاتر العمليات الستة وربطها بالمخازن والمدفوعات والحسابات | J174: المخطط التفصيلي | K174: ص 98 | L174: — | M174: نعم
A175: 171 | B175: إدارة الموارد البشرية والخدمات | C175: Human Resources & Services | D175: المشتريات | E175: Purchasing | F175: pur | H175: D3 | I175: طلب الشراء: الإنشاء من الإدارات، الاعتماد حسب الصلاحيات، متابعة الحالة | J175: المخطط التفصيلي | K175: ص 98 و65 | L175: — | M175: نعم
A176: 172 | B176: إدارة الموارد البشرية والخدمات | C176: Human Resources & Services | D176: المشتريات | E176: Purchasing | F176: pur | H176: D4 | I176: عروض الأسعار: التسجيل والاعتماد الإلكتروني، وإرسال RFQ للموردين | J176: المخطط التفصيلي | K176: ص 98 و65 | L176: — | M176: نعم
A177: 173 | B177: إدارة الموارد البشرية والخدمات | C177: Human Resources & Services | D177: المشتريات | E177: Purchasing | F177: pur | H177: D5 | I177: أوامر الشراء: الإصدار والاعتماد الإلكتروني ومتابعة الحالة | J177: المخطط التفصيلي | K177: ص 98 | L177: — | M177: نعم
A178: 174 | B178: إدارة الموارد البشرية والخدمات | C178: Human Resources & Services | D178: المشتريات | E178: Purchasing | F178: pur | H178: D6 | I178: فاتورة المشتريات وتحميلها من أمر الشراء، ومطابقة الفاتورة | J178: المخطط التفصيلي | K178: ص 98 و65 | L178: — | M178: نعم
A179: 175 | B179: إدارة الموارد البشرية والخدمات | C179: Human Resources & Services | D179: المشتريات | E179: Purchasing | F179: pur | H179: D7 | I179: مردودات المشتريات وتحميلها من الفاتورة | J179: المخطط التفصيلي | K179: ص 99 | L179: — | M179: نعم
A180: 176 | B180: إدارة الموارد البشرية والخدمات | C180: Human Resources & Services | D180: المشتريات | E180: Purchasing | F180: pur | H180: D8 | I180: الاعتمادات المستندية: فتح الاعتماد، مصاريف الاعتماد، دخول الشحنة، التسعير | J180: المخطط التفصيلي | K180: ص 65 | L180: — | M180: نعم
A181: 177 | B181: إدارة الموارد البشرية والخدمات | C181: Human Resources & Services | D181: المشتريات | E181: Purchasing | F181: pur | H181: D9 | I181: تكليف شركات شحن وتفتيش | J181: المخطط التفصيلي | K181: ص 65 | L181: — | M181: نعم
A182: 178 | B182: إدارة الموارد البشرية والخدمات | C182: Human Resources & Services | D182: المشتريات | E182: Purchasing | F182: pur | H182: D10 | I182: الخدمات التسع: إيجار مبنى، كهرباء ومقسمات، علاقات عامة، صيانة سيارات، تأمين إجباري وشامل، نثرية، تنظيف، وقود | J182: المخطط التفصيلي | K182: ص 66 | L182: — | M182: نعم
A183: 179 | B183: إدارة الموارد البشرية والخدمات | C183: Human Resources & Services | D183: المشتريات | E183: Purchasing | F183: pur | H183: D11 | I183: المشاريع: إيجارات المواقع، سداد فواتير مشتريات المشاريع | J183: المخطط التفصيلي | K183: ص 66 | L183: — | M183: نعم
... A230: 226 | B230: إدارة الموارد البشرية والخدمات | C230: Human Resources & Services | D230: المخازن | E230: Inventory / Stores | F230: inv | H230: X6 | I230: ربط الصرف بأمر عمل أو مشروع | J230: من واقع الخبرة | K230: بدونه لا تُعرف تكلفة المواد لكل موقع ومشروع | L230: — | M230: لا (مقترح)
A231: 227 | B231: إدارة الموارد البشرية والخدمات | C231: Human Resources & Services | D231: التدريب والتطوير | E231: Training & Development | F231: trn | G231: الملحق V1.2 · 2026.09.12 · تقلّص النطاق | H231: D0 | I231: BR-TRN-01 تصنيفات التدريب قابلة للإضافة والتعديل | J231: المخطط التفصيلي | K231: BRD ص 6 | L231: — | M231: نعم
A232: 228 | B232: إدارة الموارد البشرية والخدمات | C232: Human Resources & Services | D232: التدريب والتطوير | E232: Training & Development | F232: trn | G232: الملحق V1.2 · 2026.09.12 · تقلّص النطاق | H232: D1 | I232: BR-TRN-02 جهات التدريب: الاسم، النوع داخلي/خارجي، بيانات التواصل | J232: المخطط التفصيلي | K232: BRD ص 6 | L232: — | M232: نعم
A233: 229 | B233: إدارة الموارد البشرية والخدمات | C233: Human Resources & Services | D233: التدريب والتطوير | E233: Training & Development | F233: trn | G233: الملحق V1.2 · 2026.09.12 · تقلّص النطاق | H233: D2 | I233: BR-TRN-03 الدورة التدريبية: الاسم، الرمز، التصنيف، الجهة، النوع، الأسلوب، المدة | J233: المخطط التفصيلي | K233: BRD ص 6–7 | L233: — | M233: نعم
A234: 230 | B234: إدارة الموارد البشرية والخدمات | C234: Human Resources & Services | D234: التدريب والتطوير | E234: Training & Development | F234: trn | G234: الملحق V1.2 · 2026.09.12 · تقلّص النطاق | H234: D3 | I234: BR-TRN-04 تسجيل أو استيراد بنود الخطة المعتمدة خارج النظام | J234: المخطط التفصيلي | K234: BRD ص 7 | L234: — | M234: نعم
A235: 231 | B235: إدارة الموارد البشرية والخدمات | C235: Human Resources & Services | D235: التدريب والتطوير | E235: Training & Development | F235: trn | G235: الملحق V1.2 · 2026.09.12 · تقلّص النطاق | H235: D4 | I235: BR-TRN-05 متابعة وتحديث حالة تنفيذ بنود الخطة | J235: المخطط التفصيلي | K235: BRD ص 7 | L235: — | M235: نعم
A236: 232 | B236: إدارة الموارد البشرية والخدمات | C236: Human Resources & Services | D236: التدريب والتطوير | E236: Training & Development | F236: trn | G236: الملحق V1.2 · 2026.09.12 · تقلّص النطاق | H236: D5 | I236: BR-TRN-06 مرجع اعتماد الخطة الصادر خارج النظام مع مرفق | J236: المخطط التفصيلي | K236: BRD ص 7 | L236: — | M236: نعم
A237: 233 | B237: إدارة الموارد البشرية والخدمات | C237: Human Resources & Services | D237: التدريب والتطوير | E237: Training & Development | F237: trn | G237: الملحق V1.2 · 2026.09.12 · تقلّص النطاق | H237: D6 | I237: BR-TRN-07 إنشاء جلسة تدريب من بند معتمد وتحديث حالته | J237: المخطط التفصيلي | K237: BRD ص 7–8 | L237: — | M237: نعم
A238: 234 | B238: إدارة الموارد البشرية والخدمات | C238: Human Resources & Services | D238: التدريب والتطوير | E238: Training & Development | F238: trn | G238: الملحق V1.2 · 2026.09.12 · تقلّص النطاق | H238: D7 | I238: BR-TRN-08 جلسة التدريب بحالاتها الخمس ومنسّقها وموقعها | J238: المخطط التفصيلي | K238: BRD ص 8 | L238: — | M238: نعم
A239: 235 | B239: إدارة الموارد البشرية والخدمات | C239: Human Resources & Services | D239: التدريب والتطوير | E239: Training & Development | F239: trn | G239: الملحق V1.2 · 2026.09.12 · تقلّص النطاق | H239: D8 | I239: BR-TRN-09 طلب تدريب من مدير الإدارة أو القسم بأساس ثلاثي: ضمن الخطة / خارجها / مشروع | J239: المخطط التفصيلي | K239: BRD ص 8–9 | L239: — | M239: نعم
A240: 236 | B240: إدارة الموارد البشرية والخدمات | C240: Human Resources & Services | D240: التدريب والتطوير | E240: Training & Development | F240: trn | G240: الملحق V1.2 · 2026.09.12 · تقلّص النطاق | H240: D9 | I240: BR-TRN-10 تحديد موظف أو مجموعة موظفين مستهدفين داخل الطلب | J240: المخطط التفصيلي | K240: BRD ص 9 | L240: — | M240: نعم
A241: 237 | B241: إدارة الموارد البشرية والخدمات | C241: Human Resources & Services | D241: التدريب والتطوير | E241: Training & Development | F241: trn | G241: الملحق V1.2 · 2026.09.12 · تقلّص النطاق | H241: D10 | I241: BR-TRN-11 معالجة الطلب والتسجيل بواسطة مسؤول التدريب | J241: المخطط التفصيلي | K241: BRD ص 9 | L241: — | M241: نعم
A242: 238 | B242: إدارة الموارد البشرية والخدمات | C242: Human Resources & Services | D242: التدريب والتطوير | E242: Training & Development | F242: trn | G242: الملحق V1.2 · 2026.09.12 · تقلّص النطاق | H242: D11 | I242: اعتماد الإدارة العليا إلزامي للتدريب الخارجي مع مرجع القرار | J242: المخطط التفصيلي | K242: BRD ص 9–10 | L242: — | M242: نعم
... A345: 341 | B345: إدارة الموارد البشرية والخدمات | C345: Human Resources & Services | D345: إدارة المركبات | E345: Fleet Management | F345: flt | G345: الملحق V1.1 · 2026.09.12 · تقلّص النطاق | H345: X11 | I345: ترحيل سجل المركبات ووثائقها الحالية | J345: من واقع الخبرة | K345: لا بند ترحيل في الوثيقة | L345: — | M345: لا (مقترح)
A346: 342 | B346: الإدارة المالية | C346: Finance | D346: المحاسبة | E346: Accounting | F346: acc | H346: D0 | I346: دليل الحسابات ودليل مراكز التكلفة | J346: المخطط التفصيلي | K346: ص 104 | L346: — | M346: نعم
A347: 343 | B347: الإدارة المالية | C347: Finance | D347: المحاسبة | E347: Accounting | F347: acc | H347: D1 | I347: تصميم القوائم المالية والقوائم الختامية | J347: المخطط التفصيلي | K347: ص 104 | L347: — | M347: نعم
A348: 344 | B348: الإدارة المالية | C348: Finance | D348: المحاسبة | E348: Accounting | F348: acc | H348: D2 | I348: تعريف العملات واليوميات المساعدة ومميز القيد | J348: المخطط التفصيلي | K348: ص 104 | L348: — | M348: نعم
A349: 345 | B349: الإدارة المالية | C349: Finance | D349: المحاسبة | E349: Accounting | F349: acc | H349: D3 | I349: إصدار قيود اليومية وقيود فرق العملة | J349: المخطط التفصيلي | K349: ص 104 | L349: — | M349: نعم
A350: 346 | B350: الإدارة المالية | C350: Finance | D350: المحاسبة | E350: Accounting | F350: acc | H350: D4 | I350: القيد الافتتاحي لمراكز التكلفة وسجل القيود اليومية | J350: المخطط التفصيلي | K350: ص 104 | L350: — | M350: نعم
A351: 347 | B351: الإدارة المالية | C351: Finance | D351: المحاسبة | E351: Accounting | F351: acc | H351: D5 | I351: القيود الدورية | J351: المخطط التفصيلي | K351: ص 67 | L351: — | M351: نعم
A352: 348 | B352: الإدارة المالية | C352: Finance | D352: المحاسبة | E352: Accounting | F352: acc | H352: D6 | I352: اثنا عشر تقريراً: الأستاذ العام والمساعد، اليومية، ميزان المراجعة، تحليل القوائم، الموازنة التقديرية، مراكز التكلفة ومصفوفتها | J352: المخطط التفصيلي | K352: ص 104–105 | L352: — | M352: نعم
A353: 349 | B353: الإدارة المالية | C353: Finance | D353: المحاسبة | E353: Accounting | F353: acc | H353: D7 | I353: الأرصدة الافتتاحية | J353: قائمة وظائف المورّد | K353: قائمة الوظائف بند 343 | L353: يعمل تشغيلياً | M353: نعم
A354: 350 | B354: الإدارة المالية | C354: Finance | D354: المحاسبة | E354: Accounting | F354: acc | H354: D8 | I354: قيود احتساب الإيراد والمصروف الخاص بالخدمات وتوزيعه على الأشهر | J354: قائمة وظائف المورّد | K354: بند 347 | L354: يعمل تشغيلياً | M354: نعم
A355: 351 | B355: الإدارة المالية | C355: Finance | D355: المحاسبة | E355: Accounting | F355: acc | H355: D9 | I355: الميزانية العمومية وقائمة الدخل وقائمة التدفقات النقدية | J355: قائمة وظائف المورّد | K355: بند 359–361 | L355: يعمل تشغيلياً | M355: نعم
A356: 352 | B356: الإدارة المالية | C356: Finance | D356: المحاسبة | E356: Accounting | F356: acc | H356: D10 | I356: تقارير مراكز التكلفة: الأستاذ المساعد، ميزان المراجعة، تفصيلي، المصفوفة | J356: قائمة وظائف المورّد | K356: بند 355–358 | L356: يعمل تشغيلياً | M356: نعم
A357: 353 | B357: الإدارة المالية | C357: Finance | D357: المحاسبة | E357: Accounting | F357: acc | H357: X0 | I357: إقفال الفترة المحاسبية ومنع القيد بأثر رجعي | J357: من واقع الخبرة | K357: غائب عن الوثيقة؛ بدونه تتغير القوائم المعتمدة بعد إصدارها | L357: — | M357: لا (مقترح)
... A404: 400 | B404: الإدارة المالية | C404: Finance | D404: الأصول الثابتة | E404: Fixed Assets | F404: fa | H404: X5 | I404: التمييز بين الصيانة الرأسمالية والمصروفة | J404: من واقع الخبرة | K404: «تجديد وإحلال» موجود دون قاعدة تفصل ما يُرسمل عمّا يُصرف | L404: — | M404: لا (مقترح)
A405: 401 | B405: الإدارة المالية | C405: Finance | D405: الاعتمادات المستندية | E405: Letters of Credit | F405: lc | G405: وحدة غير واردة في المخطط | H405: D0 | I405: فتح الاعتماد محمّلاً من أمر الشراء، ومصاريف الاعتماد | J405: قائمة وظائف المورّد | K405: قائمة الوظائف بند 402–403 | L405: يعمل تشغيلياً | M405: نعم
A406: 402 | B406: الإدارة المالية | C406: Finance | D406: الاعتمادات المستندية | E406: Letters of Credit | F406: lc | G406: وحدة غير واردة في المخطط | H406: D1 | I406: دخول الشحنة وتحميل المصروفات الجمركية، والتسعير | J406: قائمة وظائف المورّد | K406: بند 404–405 | L406: يعمل تشغيلياً | M406: نعم
A407: 403 | B407: الإدارة المالية | C407: Finance | D407: الاعتمادات المستندية | E407: Letters of Credit | F407: lc | G407: وحدة غير واردة في المخطط | H407: D2 | I407: مد وتعلية الاعتماد | J407: قائمة وظائف المورّد | K407: بند 406 | L407: يعمل تشغيلياً | M407: نعم
A408: 404 | B408: الإدارة المالية | C408: Finance | D408: الاعتمادات المستندية | E408: Letters of Credit | F408: lc | G408: وحدة غير واردة في المخطط | H408: D3 | I408: تكليف شركات الشحن والتفتيش | J408: قائمة وظائف المورّد | K408: بند 407 | L408: يعمل تشغيلياً | M408: نعم
A409: 405 | B409: الإدارة المالية | C409: Finance | D409: الاعتمادات المستندية | E409: Letters of Credit | F409: lc | G409: وحدة غير واردة في المخطط | H409: D4 | I409: شاشة استرجاع قيمة التأمين النقدي وتحميل المصاريف كمصروف فترة | J409: قائمة وظائف المورّد | K409: بند 408 | L409: قيد التنفيذ | M409: نعم
A410: 406 | B410: الإدارة المالية | C410: Finance | D410: الاعتمادات المستندية | E410: Letters of Credit | F410: lc | G410: وحدة غير واردة في المخطط | H410: D5 | I410: شاشة طلب فتح اعتماد مستندي بمسار اعتماد إلكتروني | J410: قائمة وظائف المورّد | K410: بند 400 | L410: قيد التنفيذ | M410: نعم
...
